{
  "Setup": {
    "pageUrl": "pages/services/setup.html",
    "imageUrl": "assets/images/lights/pic03.jpg"
  },
  "Teardown": {
    "pageUrl": "pages/services/teardown.html",
    "imageUrl": "assets/images/lights/pic05.jpg"
  },
  "Maintenance": {
    "pageUrl": "pages/services/maintenance.html",
    "imageUrl": "assets/images/lights/pic04.jpg"
  },
  "Storage": {
    "pageUrl": "pages/services/storage.html",
    "imageUrl": "assets/images/lights/pic06.jpg"
  },
  "Residential": {
    "pageUrl": "pages/services/residential.html",
    "imageUrl": "assets/images/lights/pic01.jpg"
  },
  "Commercial": {
    "pageUrl": "pages/services/commercial.html",
    "imageUrl": "assets/images/lights/pic02.jpg"
  }
}

