{
  "Residential Lighting": {
    "pageUrl": "pages/services/residential-lighting.html",
    "imageUrl": "assets/images/lights/pic01.jpg",
    "icon": "fa-house"
  },
  "Commercial Lighting": {
    "pageUrl": "pages/services/commercial-lighting.html",
    "imageUrl": "assets/images/lights/pic02.jpg",
    "icon": "fa-store"
  },
  "Custom Designs": {
    "pageUrl": "pages/services/custom-designs.html",
    "imageUrl": "assets/images/lights/pic03.jpg",
    "icon": "fa-drafting-compass"
  },
  "Maintenance & Takedown": {
    "pageUrl": "pages/services/maintenance-takedown.html",
    "imageUrl": "assets/images/lights/pic04.jpg",
    "icon": "fa-toolbox"
  }
}
